ValVault/__init__.py
ValVault/auth.py
ValVault/password.py
ValVault/settings.py
ValVault/storage.py
ValVault/structs.py
ValVault-3.0.1.dist-info/LICENSE
ValVault-3.0.1.dist-info/METADATA
ValVault-3.0.1.dist-info/WHEEL
ValVault-3.0.1.dist-info/top_level.txt
ValVault-3.0.1.dist-info/RECORD
