Metadata-Version: 2.1
Name: ValVault
Version: 3.0.1
Author: PWall
License: GPL-3.0
Project-URL: Homepage, https://github.com/ValUtils/ValVault
Keywords: valorant,vault,keepass
Requires-Python: >=3.8
License-File: LICENSE
Requires-Dist: requests
Requires-Dist: pykeepass
Requires-Dist: jwt
Requires-Dist: dataclasses-json
Requires-Dist: ValLib
